pyspedfiscal/__init__.py
pyspedfiscal/campos.py
pyspedfiscal/core.py
pyspedfiscal/exception.py
pyspedfiscal/gerais.py
pyspedfiscal/models.py
pyspedfiscal/tabelas.py
pyspedfiscal/bloco_0/__init__.py
pyspedfiscal/bloco_0/core.py
pyspedfiscal/bloco_0/registro_0000.py
pyspedfiscal/bloco_0/registro_0001.py
pyspedfiscal/bloco_0/registro_0002.py
pyspedfiscal/bloco_0/registro_0005.py
pyspedfiscal/bloco_0/registro_0015.py
pyspedfiscal/bloco_0/registro_0100.py
pyspedfiscal/bloco_0/registro_0150.py
pyspedfiscal/bloco_0/registro_0175.py
pyspedfiscal/bloco_0/registro_0190.py
pyspedfiscal/bloco_0/registro_0200.py
pyspedfiscal/bloco_0/registro_0205.py
pyspedfiscal/bloco_0/registro_0206.py
pyspedfiscal/bloco_0/registro_0210.py
pyspedfiscal/bloco_0/registro_0220.py
pyspedfiscal/bloco_0/registro_0221.py
pyspedfiscal/bloco_0/registro_0300.py
pyspedfiscal/bloco_0/registro_0305.py
pyspedfiscal/bloco_0/registro_0400.py
pyspedfiscal/bloco_0/registro_0450.py
pyspedfiscal/bloco_0/registro_0460.py
pyspedfiscal/bloco_0/registro_0500.py
pyspedfiscal/bloco_0/registro_0600.py
pyspedfiscal/bloco_0/registro_0990.py
pyspedfiscal/bloco_1/__init__.py
pyspedfiscal/bloco_1/core.py
pyspedfiscal/bloco_9/__init__.py
pyspedfiscal/bloco_9/core.py
pyspedfiscal/bloco_9/registro_9001.py
pyspedfiscal/bloco_9/registro_9900.py
pyspedfiscal/bloco_9/registro_9990.py
pyspedfiscal/bloco_9/registro_9999.py
pyspedfiscal/bloco_b/__init__.py
pyspedfiscal/bloco_b/core.py
pyspedfiscal/bloco_b/registro_b001.py
pyspedfiscal/bloco_b/registro_b020.py
pyspedfiscal/bloco_b/registro_b025.py
pyspedfiscal/bloco_b/registro_b030.py
pyspedfiscal/bloco_b/registro_b035.py
pyspedfiscal/bloco_b/registro_b350.py
pyspedfiscal/bloco_b/registro_b420.py
pyspedfiscal/bloco_b/registro_b440.py
pyspedfiscal/bloco_b/registro_b460.py
pyspedfiscal/bloco_b/registro_b470.py
pyspedfiscal/bloco_b/registro_b500.py
pyspedfiscal/bloco_b/registro_b510.py
pyspedfiscal/bloco_b/registro_b990.py
pyspedfiscal/bloco_c/__init__.py
pyspedfiscal/bloco_c/core.py
pyspedfiscal1-0.2.10.dist-info/licenses/LICENCE
pyspedfiscal1-0.2.10.dist-info/METADATA
pyspedfiscal1-0.2.10.dist-info/WHEEL
pyspedfiscal1-0.2.10.dist-info/top_level.txt
pyspedfiscal1-0.2.10.dist-info/RECORD
