Metadata-Version: 2.4
Name: pyspedfiscal1
Version: 0.2.10
Summary: Serializa um arquivo do tipo SPED Fiscal
Home-page: https://github.com/Renanmarini/pyspedfiscal2
Author: ['Rodolfo Scarp', 'Renan Marini']
Author-email: ['rodolfoscarp@gmail.com', 'renan.marini@jrcontabiltr.com.br']
License: MIT License
Keywords: spedfiscal
License-File: LICENCE
Requires-Dist: pydantic
Dynamic: author
Dynamic: author-email
Dynamic: description
Dynamic: description-content-type
Dynamic: home-page
Dynamic: keywords
Dynamic: license
Dynamic: license-file
Dynamic: requires-dist
Dynamic: summary
